socli/__init__.py
socli/__main__.py
socli/auth.py
socli/parser.py
socli/printer.py
socli/search.py
socli/sentry.py
socli/socli.py
socli/tui.py
socli/user.py
socli/user_agents.txt
socli/version.py
socli/tests/__init__.py
socli/tests/test_socli.py
socli-7.3.data/data/man/man1/socli.1
socli-7.3.dist-info/LICENSE
socli-7.3.dist-info/METADATA
socli-7.3.dist-info/WHEEL
socli-7.3.dist-info/entry_points.txt
socli-7.3.dist-info/top_level.txt
socli-7.3.dist-info/RECORD
