Metadata-Version: 2.1
Name: socli
Version: 7.3
Summary: Stack overflow command line interface. SoCLI allows you to search and browse stack overflow from the terminal.
Home-page: https://www.github.com/gautamkrishnar/socli
Author: Gautam Krishna R
Author-email: r.gautamkrishna@gmail.com
License: BSD
Keywords: stack overflow cli
Platform: UNKNOWN
Classifier: License :: OSI Approved :: BSD License
Classifier: Programming Language :: Python :: 3.5
Classifier: Programming Language :: Python :: 3.6
Classifier: Programming Language :: Python :: 3.7
Classifier: Programming Language :: Python :: 3.8
Requires: BeautifulSoup4
Requires: requests
Requires: colorama
Requires: PyStackExchange
Requires: sentry_sdk
Requires: urwid
Requires-Python: >=3.5.0
Requires-Dist: BeautifulSoup4
Requires-Dist: requests
Requires-Dist: colorama
Requires-Dist: Py-stackExchange
Requires-Dist: sentry-sdk
Requires-Dist: urwid
Requires-Dist: argcomplete
